GUIskew/__init__.py
GUIskew/__main__.py
GUIskew-0.1.2.dist-info/LICENSE
GUIskew-0.1.2.dist-info/METADATA
GUIskew-0.1.2.dist-info/WHEEL
GUIskew-0.1.2.dist-info/top_level.txt
GUIskew-0.1.2.dist-info/RECORD
