Metadata-Version: 2.1
Name: GUIskew
Version: 0.1.2
Summary: A program that calculates genskew.
Home-page: https://genskew.csb.univie.ac.at/guiskew
Author: Thomas Rattei, Julius Krämer
License: Creative Commons
Classifier: Programming Language :: Python :: 3
Classifier: Operating System :: OS Independent
Requires-Python: >=3.6
License-File: LICENSE
Requires-Dist: matplotlib
Requires-Dist: Genskew-univiecube
Requires-Dist: Genskew-cc
